compressbinarytable/__init__.py
compressbinarytable/compressbinarytable.py
compressbinarytable-0.2.0.dist-info/entry_points.txt
compressbinarytable-0.2.0.dist-info/METADATA
compressbinarytable-0.2.0.dist-info/WHEEL
compressbinarytable-0.2.0.dist-info/RECORD
