Metadata-Version: 2.1
Name: compressbinarytable
Version: 0.2.0
Summary: Compression of binary table
Home-page: https://github.com/kalininalab/CompressBinaryTable
Author: Alper Yurtseven
Author-email: alper.yurtseven@helmholtz-hips.de
Requires-Python: >=3.8,<4.0
Classifier: Development Status :: 3 - Alpha
Classifier: Operating System :: OS Independent
Classifier: Programming Language :: Python :: 3
Classifier: Programming Language :: Python :: 3.8
Classifier: Programming Language :: Python :: 3.9
Classifier: Programming Language :: Python :: 3.10
Classifier: Programming Language :: Python :: 3.11
Requires-Dist: numpy (>=1.21.4,<2.0.0)
Requires-Dist: pandas (>=1.5.3,<2.0.0)
Project-URL: Repository, https://github.com/kalininalab/CompressBinaryTable
